bot/__init__.py
bot/_version.py
bot/common.py
bot/dl_gui.py
bot/duel_links_runtime.py
bot/images_qr.py
bot/shared.py
bot/test_duelLinkRunTimeOptions.py
bot/providers/__init__.py
bot/providers/actions.py
bot/providers/common.py
bot/providers/duellinks.py
bot/providers/misc.py
bot/providers/predefined.py
bot/providers/provider.py
bot/providers/shared.py
bot/providers/trainer_matches.py
bot/providers/nox/__init__.py
bot/providers/nox/nox.py
bot/providers/nox/predefined.py
bot/utils/__init__.py
bot/utils/algo.py
bot/utils/common.py
bot/utils/data.py
bot/utils/watcher.py
yugioh_bot-0.6.3.dist-info/DESCRIPTION.rst
yugioh_bot-0.6.3.dist-info/METADATA
yugioh_bot-0.6.3.dist-info/RECORD
yugioh_bot-0.6.3.dist-info/WHEEL
yugioh_bot-0.6.3.dist-info/metadata.json
yugioh_bot-0.6.3.dist-info/top_level.txt
