Metadata-Version: 2.0
Name: yugioh-bot
Version: 0.6.3
Summary: Botting Yugioh-DuelLinks
Home-page: https://github.com/will7200/Yugioh-bot
Maintainer: will7200
Maintainer-email: yugiohbotgit@gmail.com
License: UNKNOWN
